{"cameraMode":{"drawMode":0,"name":"Shaded","section":"Shading Mode"},"sceneLighting":false,"audioPlay":false,"sceneViewState":{"m_AlwaysRefresh":false,"showFog":true,"showSkybox":false,"showFlares":true,"showImageEffects":true,"showParticleSystems":true,"showVisualEffectGraphs":true,"m_FxEnabled":true},"in2DMode":false,"pivot":{"x":7.1020917892456059,"y":7.925455570220947,"z":4.176861763000488},"rotation":{"x":-0.04172906652092934,"y":0.9122685194015503,"z":-0.09614171832799912,"w":-0.39595815539360049},"size":9.708131790161133,"orthographic":false}